chainlink_web3/__init__.py
chainlink_web3/abis.py
chainlink_web3/types.py
chainlink_web3/utils.py
chainlink_web3-0.1.4.dist-info/METADATA
chainlink_web3-0.1.4.dist-info/WHEEL
chainlink_web3-0.1.4.dist-info/top_level.txt
chainlink_web3-0.1.4.dist-info/RECORD
