Metadata-Version: 2.1
Name: chainlink-web3
Version: 0.1.4
Summary: Library for interacting with Chainlink Ethereum contracts.
Home-page: https://github.com/kalmiallc/chainlink-web3
Author: Kalmia LTD
Author-email: itkalmia@kalmia.si
License: MIT license
Platform: UNKNOWN
